setup.py
RocStat/Binomialdistribution.py
RocStat/Gaussiandistribution.py
RocStat/Generaldistribution.py
RocStat/__init__.py
RocStat.egg-info/PKG-INFO
RocStat.egg-info/SOURCES.txt
RocStat.egg-info/dependency_links.txt
RocStat.egg-info/not-zip-safe
RocStat.egg-info/top_level.txt