Metadata-Version: 1.0
Name: RocStat
Version: 0.1
Summary: Gaussian and binomial distributions
Home-page: UNKNOWN
Author: Allan Ruan
Author-email: allanruan1@gmail.com
License: UNKNOWN
Platform: UNKNOWN
